agox_extra/__init__.py
agox_extra/jax/__init__.py
agox_extra/jax/fingerprint/__init__.py
agox_extra/jax/fingerprint/fingerprint_jax.py
agox_extra/jax/fingerprint/utils.py
agox_extra/shepherd/__init__.py
agox_extra/shepherd/context_observer.py
agox_extra/symmetry/__init__.py
agox_extra/symmetry/symmetry.py
agox_extra/symmetry/symmetry_permutation.py
agox_extra/symmetry/symmetry_rattle.py
agox_extra/symmetry/symmetry_utils/__init__.py
agox_extra/symmetry/symmetry_utils/symmetry_enforcer.py
agox_extra/symmetry/symmetry_utils/symmetry_groups.py
agox_extra-0.1.0.dist-info/METADATA
agox_extra-0.1.0.dist-info/WHEEL
agox_extra-0.1.0.dist-info/entry_points.txt
agox_extra-0.1.0.dist-info/RECORD
